<?xml version="1.0" encoding="UTF-8" ?>
<!DOCTYPE mapper PUBLIC "-//mybatis.org//DTD Mapper 3.0//EN" "http://mybatis.org/dtd/mybatis-3-mapper.dtd" >
<mapper namespace="com.aidou.dao.mapper.TbCommentMapper" >
  <resultMap id="BaseResultMap" type="com.aidou.dao.entity.TbComment" >
    <!--
      WARNING - @mbggenerated
      This element is automatically generated by MyBatis Generator, do not modify.
      This element was generated on Mon Dec 30 20:11:45 CST 2019.
    -->
    <id column="id" property="id" jdbcType="BIGINT" />
    <result column="articleid" property="articleid" jdbcType="BIGINT" />
    <result column="content" property="content" jdbcType="VARCHAR" />
    <result column="uid" property="uid" jdbcType="BIGINT" />
    <result column="parentid" property="parentid" jdbcType="BIGINT" />
    <result column="created" property="created" jdbcType="TIMESTAMP" />
    <result column="updated" property="updated" jdbcType="TIMESTAMP" />
    <result column="to_uid" property="toUid" jdbcType="BIGINT" />
    <result column="dp_status" property="dpStatus" jdbcType="INTEGER" />
    <result column="thumbup_count" property="thumbupCount" jdbcType="BIGINT" />
    <result column="comment_count" property="commentCount" jdbcType="BIGINT" />
  </resultMap>
  <sql id="Example_Where_Clause" >
    <!--
      WARNING - @mbggenerated
      This element is automatically generated by MyBatis Generator, do not modify.
      This element was generated on Mon Dec 30 20:11:45 CST 2019.
    -->
    <where >
      <foreach collection="oredCriteria" item="criteria" separator="or" >
        <if test="criteria.valid" >
          <trim prefix="(" suffix=")" prefixOverrides="and" >
            <foreach collection="criteria.criteria" item="criterion" >
              <choose >
                <when test="criterion.noValue" >
                  and ${criterion.condition}
                </when>
                <when test="criterion.singleValue" >
                  and ${criterion.condition} #{criterion.value}
                </when>
                <when test="criterion.betweenValue" >
                  and ${criterion.condition} #{criterion.value} and #{criterion.secondValue}
                </when>
                <when test="criterion.listValue" >
                  and ${criterion.condition}
                  <foreach collection="criterion.value" item="listItem" open="(" close=")" separator="," >
                    #{listItem}
                  </foreach>
                </when>
              </choose>
            </foreach>
          </trim>
        </if>
      </foreach>
    </where>
  </sql>
  <sql id="Update_By_Example_Where_Clause" >
    <!--
      WARNING - @mbggenerated
      This element is automatically generated by MyBatis Generator, do not modify.
      This element was generated on Mon Dec 30 20:11:45 CST 2019.
    -->
    <where >
      <foreach collection="example.oredCriteria" item="criteria" separator="or" >
        <if test="criteria.valid" >
          <trim prefix="(" suffix=")" prefixOverrides="and" >
            <foreach collection="criteria.criteria" item="criterion" >
              <choose >
                <when test="criterion.noValue" >
                  and ${criterion.condition}
                </when>
                <when test="criterion.singleValue" >
                  and ${criterion.condition} #{criterion.value}
                </when>
                <when test="criterion.betweenValue" >
                  and ${criterion.condition} #{criterion.value} and #{criterion.secondValue}
                </when>
                <when test="criterion.listValue" >
                  and ${criterion.condition}
                  <foreach collection="criterion.value" item="listItem" open="(" close=")" separator="," >
                    #{listItem}
                  </foreach>
                </when>
              </choose>
            </foreach>
          </trim>
        </if>
      </foreach>
    </where>
  </sql>
  <sql id="Base_Column_List" >
    <!--
      WARNING - @mbggenerated
      This element is automatically generated by MyBatis Generator, do not modify.
      This element was generated on Mon Dec 30 20:11:45 CST 2019.
    -->
    id, articleid, content, uid, parentid, created, updated, to_uid, dp_status, thumbup_count, 
    comment_count
  </sql>
  <select id="selectByExample" resultMap="BaseResultMap" parameterType="com.aidou.dao.entity.TbCommentExample" >
    <!--
      WARNING - @mbggenerated
      This element is automatically generated by MyBatis Generator, do not modify.
      This element was generated on Mon Dec 30 20:11:45 CST 2019.
    -->
    select
    <if test="distinct" >
      distinct
    </if>
    <include refid="Base_Column_List" />
    from tb_comment
    <if test="_parameter != null" >
      <include refid="Example_Where_Clause" />
    </if>
    <if test="orderByClause != null" >
      order by ${orderByClause}
    </if>
  </select>
  <select id="selectByPrimaryKey" resultMap="BaseResultMap" parameterType="java.lang.Long" >
    <!--
      WARNING - @mbggenerated
      This element is automatically generated by MyBatis Generator, do not modify.
      This element was generated on Mon Dec 30 20:11:45 CST 2019.
    -->
    select 
    <include refid="Base_Column_List" />
    from tb_comment
    where id = #{id,jdbcType=BIGINT}
  </select>
  <delete id="deleteByPrimaryKey" parameterType="java.lang.Long" >
    <!--
      WARNING - @mbggenerated
      This element is automatically generated by MyBatis Generator, do not modify.
      This element was generated on Mon Dec 30 20:11:45 CST 2019.
    -->
    delete from tb_comment
    where id = #{id,jdbcType=BIGINT}
  </delete>
  <delete id="deleteByExample" parameterType="com.aidou.dao.entity.TbCommentExample" >
    <!--
      WARNING - @mbggenerated
      This element is automatically generated by MyBatis Generator, do not modify.
      This element was generated on Mon Dec 30 20:11:45 CST 2019.
    -->
    delete from tb_comment
    <if test="_parameter != null" >
      <include refid="Example_Where_Clause" />
    </if>
  </delete>
  <insert id="insert" parameterType="com.aidou.dao.entity.TbComment" >
    <!--
      WARNING - @mbggenerated
      This element is automatically generated by MyBatis Generator, do not modify.
      This element was generated on Mon Dec 30 20:11:45 CST 2019.
    -->
    insert into tb_comment (id, articleid, content, 
      uid, parentid, created, 
      updated, to_uid, dp_status, 
      thumbup_count, comment_count)
    values (#{id,jdbcType=BIGINT}, #{articleid,jdbcType=BIGINT}, #{content,jdbcType=VARCHAR}, 
      #{uid,jdbcType=BIGINT}, #{parentid,jdbcType=BIGINT}, #{created,jdbcType=TIMESTAMP}, 
      #{updated,jdbcType=TIMESTAMP}, #{toUid,jdbcType=BIGINT}, #{dpStatus,jdbcType=INTEGER}, 
      #{thumbupCount,jdbcType=BIGINT}, #{commentCount,jdbcType=BIGINT})
  </insert>
  <insert id="insertSelective"  useGeneratedKeys="true" keyProperty="id" keyColumn="id" parameterType="com.aidou.dao.entity.TbComment" >
    <!--
      WARNING - @mbggenerated
      This element is automatically generated by MyBatis Generator, do not modify.
      This element was generated on Mon Dec 30 20:11:45 CST 2019.
    -->
    insert into tb_comment
    <trim prefix="(" suffix=")" suffixOverrides="," >
      <if test="id != null" >
        id,
      </if>
      <if test="articleid != null" >
        articleid,
      </if>
      <if test="content != null" >
        content,
      </if>
      <if test="uid != null" >
        uid,
      </if>
      <if test="parentid != null" >
        parentid,
      </if>
      <if test="created != null" >
        created,
      </if>
      <if test="updated != null" >
        updated,
      </if>
      <if test="toUid != null" >
        to_uid,
      </if>
      <if test="dpStatus != null" >
        dp_status,
      </if>
      <if test="thumbupCount != null" >
        thumbup_count,
      </if>
      <if test="commentCount != null" >
        comment_count,
      </if>
    </trim>
    <trim prefix="values (" suffix=")" suffixOverrides="," >
      <if test="id != null" >
        #{id,jdbcType=BIGINT},
      </if>
      <if test="articleid != null" >
        #{articleid,jdbcType=BIGINT},
      </if>
      <if test="content != null" >
        #{content,jdbcType=VARCHAR},
      </if>
      <if test="uid != null" >
        #{uid,jdbcType=BIGINT},
      </if>
      <if test="parentid != null" >
        #{parentid,jdbcType=BIGINT},
      </if>
      <if test="created != null" >
        #{created,jdbcType=TIMESTAMP},
      </if>
      <if test="updated != null" >
        #{updated,jdbcType=TIMESTAMP},
      </if>
      <if test="toUid != null" >
        #{toUid,jdbcType=BIGINT},
      </if>
      <if test="dpStatus != null" >
        #{dpStatus,jdbcType=INTEGER},
      </if>
      <if test="thumbupCount != null" >
        #{thumbupCount,jdbcType=BIGINT},
      </if>
      <if test="commentCount != null" >
        #{commentCount,jdbcType=BIGINT},
      </if>
    </trim>
  </insert>
  <select id="countByExample" parameterType="com.aidou.dao.entity.TbCommentExample" resultType="java.lang.Integer" >
    <!--
      WARNING - @mbggenerated
      This element is automatically generated by MyBatis Generator, do not modify.
      This element was generated on Mon Dec 30 20:11:45 CST 2019.
    -->
    select count(*) from tb_comment
    <if test="_parameter != null" >
      <include refid="Example_Where_Clause" />
    </if>
  </select>
  <update id="updateByExampleSelective" parameterType="map" >
    <!--
      WARNING - @mbggenerated
      This element is automatically generated by MyBatis Generator, do not modify.
      This element was generated on Mon Dec 30 20:11:45 CST 2019.
    -->
    update tb_comment
    <set >
      <if test="record.id != null" >
        id = #{record.id,jdbcType=BIGINT},
      </if>
      <if test="record.articleid != null" >
        articleid = #{record.articleid,jdbcType=BIGINT},
      </if>
      <if test="record.content != null" >
        content = #{record.content,jdbcType=VARCHAR},
      </if>
      <if test="record.uid != null" >
        uid = #{record.uid,jdbcType=BIGINT},
      </if>
      <if test="record.parentid != null" >
        parentid = #{record.parentid,jdbcType=BIGINT},
      </if>
      <if test="record.created != null" >
        created = #{record.created,jdbcType=TIMESTAMP},
      </if>
      <if test="record.updated != null" >
        updated = #{record.updated,jdbcType=TIMESTAMP},
      </if>
      <if test="record.toUid != null" >
        to_uid = #{record.toUid,jdbcType=BIGINT},
      </if>
      <if test="record.dpStatus != null" >
        dp_status = #{record.dpStatus,jdbcType=INTEGER},
      </if>
      <if test="record.thumbupCount != null" >
        thumbup_count = #{record.thumbupCount,jdbcType=BIGINT},
      </if>
      <if test="record.commentCount != null" >
        comment_count = #{record.commentCount,jdbcType=BIGINT},
      </if>
    </set>
    <if test="_parameter != null" >
      <include refid="Update_By_Example_Where_Clause" />
    </if>
  </update>
  <update id="updateByExample" parameterType="map" >
    <!--
      WARNING - @mbggenerated
      This element is automatically generated by MyBatis Generator, do not modify.
      This element was generated on Mon Dec 30 20:11:45 CST 2019.
    -->
    update tb_comment
    set id = #{record.id,jdbcType=BIGINT},
      articleid = #{record.articleid,jdbcType=BIGINT},
      content = #{record.content,jdbcType=VARCHAR},
      uid = #{record.uid,jdbcType=BIGINT},
      parentid = #{record.parentid,jdbcType=BIGINT},
      created = #{record.created,jdbcType=TIMESTAMP},
      updated = #{record.updated,jdbcType=TIMESTAMP},
      to_uid = #{record.toUid,jdbcType=BIGINT},
      dp_status = #{record.dpStatus,jdbcType=INTEGER},
      thumbup_count = #{record.thumbupCount,jdbcType=BIGINT},
      comment_count = #{record.commentCount,jdbcType=BIGINT}
    <if test="_parameter != null" >
      <include refid="Update_By_Example_Where_Clause" />
    </if>
  </update>
  <update id="updateByPrimaryKeySelective" parameterType="com.aidou.dao.entity.TbComment" >
    <!--
      WARNING - @mbggenerated
      This element is automatically generated by MyBatis Generator, do not modify.
      This element was generated on Mon Dec 30 20:11:45 CST 2019.
    -->
    update tb_comment
    <set >
      <if test="articleid != null" >
        articleid = #{articleid,jdbcType=BIGINT},
      </if>
      <if test="content != null" >
        content = #{content,jdbcType=VARCHAR},
      </if>
      <if test="uid != null" >
        uid = #{uid,jdbcType=BIGINT},
      </if>
      <if test="parentid != null" >
        parentid = #{parentid,jdbcType=BIGINT},
      </if>
      <if test="created != null" >
        created = #{created,jdbcType=TIMESTAMP},
      </if>
      <if test="updated != null" >
        updated = #{updated,jdbcType=TIMESTAMP},
      </if>
      <if test="toUid != null" >
        to_uid = #{toUid,jdbcType=BIGINT},
      </if>
      <if test="dpStatus != null" >
        dp_status = #{dpStatus,jdbcType=INTEGER},
      </if>
      <if test="thumbupCount != null" >
        thumbup_count = #{thumbupCount,jdbcType=BIGINT},
      </if>
      <if test="commentCount != null" >
        comment_count = #{commentCount,jdbcType=BIGINT},
      </if>
    </set>
    where id = #{id,jdbcType=BIGINT}
  </update>
  <update id="updateByPrimaryKey" parameterType="com.aidou.dao.entity.TbComment" >
    <!--
      WARNING - @mbggenerated
      This element is automatically generated by MyBatis Generator, do not modify.
      This element was generated on Mon Dec 30 20:11:45 CST 2019.
    -->
    update tb_comment
    set articleid = #{articleid,jdbcType=BIGINT},
      content = #{content,jdbcType=VARCHAR},
      uid = #{uid,jdbcType=BIGINT},
      parentid = #{parentid,jdbcType=BIGINT},
      created = #{created,jdbcType=TIMESTAMP},
      updated = #{updated,jdbcType=TIMESTAMP},
      to_uid = #{toUid,jdbcType=BIGINT},
      dp_status = #{dpStatus,jdbcType=INTEGER},
      thumbup_count = #{thumbupCount,jdbcType=BIGINT},
      comment_count = #{commentCount,jdbcType=BIGINT}
    where id = #{id,jdbcType=BIGINT}
  </update>
</mapper>